{
  "firstLayout": "",
  "gdVersion": {
    "build": 99,
    "major": 4,
    "minor": 0,
    "revision": 0
  },
  "properties": {
    "adaptGameResolutionAtRuntime": true,
    "folderProject": false,
    "orientation": "landscape",
    "packageName": "com.example.gamename",
    "pixelsRounding": false,
    "projectUuid": "20f89a6f-020e-4b52-9246-295e912b2684",
    "scaleMode": "linear",
    "sizeOnStartupMode": "adaptWidth",
    "templateSlug": "",
    "useExternalSourceFiles": false,
    "version": "1.0.0",
    "name": "LudumDare51",
    "description": "",
    "author": "",
    "windowWidth": 800,
    "windowHeight": 600,
    "latestCompilationDirectory": "",
    "maxFPS": 60,
    "minFPS": 20,
    "verticalSync": false,
    "platformSpecificAssets": {},
    "loadingScreen": {
      "backgroundColor": 0,
      "backgroundFadeInDuration": 0.2,
      "backgroundImageResourceName": "",
      "gdevelopLogoStyle": "light",
      "logoAndProgressFadeInDuration": 0.2,
      "logoAndProgressLogoFadeInDelay": 0.2,
      "minDuration": 1.5,
      "progressBarColor": 16777215,
      "progressBarHeight": 20,
      "progressBarMaxWidth": 200,
      "progressBarMinWidth": 40,
      "progressBarWidthPercent": 30,
      "showGDevelopSplash": true,
      "showProgressBar": true
    },
    "authorIds": [],
    "categories": [],
    "playableDevices": [],
    "extensionProperties": [],
    "platforms": [
      {
        "name": "GDevelop JS platform"
      }
    ],
    "currentPlatform": "GDevelop JS platform"
  },
  "resources": {
    "resources": [
      {
        "alwaysLoaded": false,
        "file": "Assets/Art/Player/player1.png",
        "kind": "image",
        "metadata": "",
        "name": "Assets\\Art\\Player\\player1.png",
        "smoothed": false,
        "userAdded": false
      },
      {
        "alwaysLoaded": false,
        "file": "Assets/Art/Player/player2.png",
        "kind": "image",
        "metadata": "",
        "name": "Assets\\Art\\Player\\player2.png",
        "smoothed": false,
        "userAdded": false
      },
      {
        "alwaysLoaded": false,
        "file": "Assets/Art/Player/player3.png",
        "kind": "image",
        "metadata": "",
        "name": "Assets\\Art\\Player\\player3.png",
        "smoothed": false,
        "userAdded": false
      },
      {
        "alwaysLoaded": false,
        "file": "Assets/Art/Player/player4.png",
        "kind": "image",
        "metadata": "",
        "name": "Assets\\Art\\Player\\player4.png",
        "smoothed": false,
        "userAdded": false
      }
    ],
    "resourceFolders": []
  },
  "objects": [],
  "objectsGroups": [],
  "variables": [],
  "layouts": [
    {
      "b": 209,
      "disableInputWhenNotFocused": true,
      "mangledName": "Untitled_32scene",
      "name": "Untitled scene",
      "oglFOV": 90,
      "oglZFar": 500,
      "oglZNear": 1,
      "r": 209,
      "standardSortMethod": true,
      "stopSoundsOnStartup": true,
      "title": "",
      "v": 209,
      "uiSettings": {
        "grid": false,
        "gridType": "rectangular",
        "gridWidth": 32,
        "gridHeight": 32,
        "gridOffsetX": 0,
        "gridOffsetY": 0,
        "gridColor": 10401023,
        "gridAlpha": 0.8,
        "snap": false,
        "zoomFactor": 0.7599999999999998,
        "windowMask": false
      },
      "objectsGroups": [],
      "variables": [],
      "instances": [
        {
          "angle": 0,
          "customSize": false,
          "height": 0,
          "layer": "",
          "name": "Player",
          "persistentUuid": "cf2a077b-7dfb-4207-81e6-09a3813ffa6d",
          "width": 0,
          "x": 361,
          "y": 223,
          "zOrder": 1,
          "numberProperties": [],
          "stringProperties": [],
          "initialVariables": []
        }
      ],
      "objects": [
        {
          "assetStoreId": "",
          "name": "Player",
          "tags": "",
          "type": "Sprite",
          "updateIfNotVisible": false,
          "variables": [],
          "effects": [],
          "behaviors": [
            {
              "name": "PointToMouse",
              "type": "PointToMouse::PointToMouse",
              "Offset": 90
            },
            {
              "acceleration": 400,
              "allowDiagonals": true,
              "angleOffset": 0,
              "angularMaxSpeed": 180,
              "customIsometryAngle": 30,
              "deceleration": 10000,
              "ignoreDefaultControls": false,
              "maxSpeed": 200,
              "movementAngleOffset": 0,
              "name": "TopDownMovement",
              "rotateObject": false,
              "type": "TopDownMovementBehavior::TopDownMovementBehavior",
              "viewpoint": "TopDown"
            }
          ],
          "animations": [
            {
              "name": "idle",
              "useMultipleDirections": false,
              "directions": [
                {
                  "looping": true,
                  "timeBetweenFrames": 0.08,
                  "sprites": [
                    {
                      "hasCustomCollisionMask": false,
                      "image": "Assets\\Art\\Player\\player1.png",
                      "points": [],
                      "originPoint": {
                        "name": "origine",
                        "x": 0,
                        "y": 0
                      },
                      "centerPoint": {
                        "automatic": true,
                        "name": "centre",
                        "x": 0,
                        "y": 0
                      },
                      "customCollisionMask": []
                    }
                  ]
                }
              ]
            },
            {
              "name": "move",
              "useMultipleDirections": false,
              "directions": [
                {
                  "looping": true,
                  "timeBetweenFrames": 0.125,
                  "sprites": [
                    {
                      "hasCustomCollisionMask": false,
                      "image": "Assets\\Art\\Player\\player1.png",
                      "points": [],
                      "originPoint": {
                        "name": "origine",
                        "x": 0,
                        "y": 0
                      },
                      "centerPoint": {
                        "automatic": true,
                        "name": "centre",
                        "x": 0,
                        "y": 0
                      },
                      "customCollisionMask": []
                    },
                    {
                      "hasCustomCollisionMask": false,
                      "image": "Assets\\Art\\Player\\player2.png",
                      "points": [],
                      "originPoint": {
                        "name": "origine",
                        "x": 0,
                        "y": 0
                      },
                      "centerPoint": {
                        "automatic": true,
                        "name": "centre",
                        "x": 0,
                        "y": 0
                      },
                      "customCollisionMask": []
                    },
                    {
                      "hasCustomCollisionMask": false,
                      "image": "Assets\\Art\\Player\\player3.png",
                      "points": [],
                      "originPoint": {
                        "name": "origine",
                        "x": 0,
                        "y": 0
                      },
                      "centerPoint": {
                        "automatic": true,
                        "name": "centre",
                        "x": 0,
                        "y": 0
                      },
                      "customCollisionMask": []
                    },
                    {
                      "hasCustomCollisionMask": false,
                      "image": "Assets\\Art\\Player\\player4.png",
                      "points": [],
                      "originPoint": {
                        "name": "origine",
                        "x": 0,
                        "y": 0
                      },
                      "centerPoint": {
                        "automatic": true,
                        "name": "centre",
                        "x": 0,
                        "y": 0
                      },
                      "customCollisionMask": []
                    }
                  ]
                }
              ]
            }
          ]
        }
      ],
      "events": [
        {
          "type": "BuiltinCommonInstructions::Standard",
          "conditions": [],
          "actions": []
        }
      ],
      "layers": [
        {
          "ambientLightColorB": 32,
          "ambientLightColorG": 0,
          "ambientLightColorR": 0,
          "followBaseLayerCamera": false,
          "isLightingLayer": false,
          "name": "",
          "visibility": true,
          "cameras": [
            {
              "defaultSize": true,
              "defaultViewport": true,
              "height": 0,
              "viewportBottom": 1,
              "viewportLeft": 0,
              "viewportRight": 1,
              "viewportTop": 0,
              "width": 0
            }
          ],
          "effects": []
        }
      ],
      "behaviorsSharedData": [
        {
          "name": "PointToMouse",
          "type": "PointToMouse::PointToMouse"
        },
        {
          "name": "TopDownMovement",
          "type": "TopDownMovementBehavior::TopDownMovementBehavior"
        }
      ]
    }
  ],
  "externalEvents": [],
  "eventsFunctionsExtensions": [
    {
      "author": "",
      "category": "",
      "description": "",
      "extensionNamespace": "",
      "fullName": "",
      "helpPath": "",
      "iconUrl": "",
      "name": "BossMovement",
      "previewIconUrl": "",
      "shortDescription": "",
      "version": "",
      "tags": [],
      "authorIds": [],
      "dependencies": [],
      "eventsFunctions": [],
      "eventsBasedBehaviors": []
    },
    {
      "author": "",
      "category": "",
      "description": "",
      "extensionNamespace": "",
      "fullName": "",
      "helpPath": "",
      "iconUrl": "",
      "name": "PointToMouse",
      "previewIconUrl": "",
      "shortDescription": "",
      "version": "",
      "tags": [],
      "authorIds": [],
      "dependencies": [],
      "eventsFunctions": [],
      "eventsBasedBehaviors": [
        {
          "description": "",
          "fullName": "",
          "name": "PointToMouse",
          "objectType": "",
          "eventsFunctions": [
            {
              "description": "",
              "fullName": "",
              "functionType": "Action",
              "group": "",
              "name": "doStepPreEvents",
              "private": false,
              "sentence": "",
              "events": [
                {
                  "type": "BuiltinCommonInstructions::Standard",
                  "conditions": [],
                  "actions": [
                    {
                      "type": {
                        "value": "RotateTowardPosition"
                      },
                      "parameters": [
                        "Object",
                        "MouseX()",
                        "MouseY()",
                        "0",
                        ""
                      ]
                    },
                    {
                      "type": {
                        "value": "SetAngle"
                      },
                      "parameters": [
                        "Object",
                        "=",
                        "Object.Angle()+ Object.Behavior::PropertyOffset()"
                      ]
                    }
                  ]
                }
              ],
              "parameters": [
                {
                  "codeOnly": false,
                  "defaultValue": "",
                  "description": "Object",
                  "longDescription": "",
                  "name": "Object",
                  "optional": false,
                  "supplementaryInformation": "",
                  "type": "object"
                },
                {
                  "codeOnly": false,
                  "defaultValue": "",
                  "description": "Behavior",
                  "longDescription": "",
                  "name": "Behavior",
                  "optional": false,
                  "supplementaryInformation": "PointToMouse::PointToMouse",
                  "type": "behavior"
                }
              ],
              "objectGroups": []
            }
          ],
          "propertyDescriptors": [
            {
              "value": "0",
              "type": "Number",
              "label": "Offset",
              "description": "",
              "group": "",
              "extraInformation": [],
              "hidden": false,
              "name": "Offset"
            }
          ]
        }
      ]
    }
  ],
  "externalLayouts": [
    {
      "associatedLayout": "",
      "name": "Untitled external layout",
      "instances": [],
      "editionSettings": {}
    }
  ],
  "externalSourceFiles": []
}